{
  "version": "7",
  "dialect": "postgresql",
  "entries": [
    {
      "idx": 0,
      "version": "7",
      "when": 1780751673939,
      "tag": "0000_init",
      "breakpoints": true
    },
    {
      "idx": 1,
      "version": "7",
      "when": 1780762890493,
      "tag": "0001_add_reaction_trigger",
      "breakpoints": true
    },
    {
      "idx": 2,
      "version": "7",
      "when": 1780841233431,
      "tag": "0002_majestic_spacker_dave",
      "breakpoints": true
    },
    {
      "idx": 3,
      "version": "7",
      "when": 1780842370904,
      "tag": "0003_material_red_hulk",
      "breakpoints": true
    },
    {
      "idx": 4,
      "version": "7",
      "when": 1780851755015,
      "tag": "0004_hot_norrin_radd",
      "breakpoints": true
    }
  ]
}